dnscheck/__init__.py
dnscheck/cli.py
dnscheck/dns_info.py
dnscheck/logger.py
dnscheck/reachablity.py
dnscheck/resolver.py
py_dnscheck-1.0.1.dist-info/METADATA
py_dnscheck-1.0.1.dist-info/WHEEL
py_dnscheck-1.0.1.dist-info/entry_points.txt
py_dnscheck-1.0.1.dist-info/top_level.txt
py_dnscheck-1.0.1.dist-info/RECORD
