Metadata-Version: 2.4
Name: py-dnscheck
Version: 1.0.1
Summary: A Python module to perform DNS resolution, health check and configuration.
Author: Santhosh Murugesan
Author-email: santhoshm.murugesan@gmail.com
Classifier: Programming Language :: Python :: 3
Classifier: Operating System :: POSIX :: Linux
Classifier: Operating System :: Microsoft :: Windows
Requires-Python: >=3.6
Requires-Dist: dnspython
Dynamic: author
Dynamic: author-email
Dynamic: classifier
Dynamic: description
Dynamic: description-content-type
Dynamic: requires-dist
Dynamic: requires-python
Dynamic: summary
